causaliq_workflow/__init__.py
causaliq_workflow/action.py
causaliq_workflow/cli.py
causaliq_workflow/logger.py
causaliq_workflow/registry.py
causaliq_workflow/schema.py
causaliq_workflow/status.py
causaliq_workflow/workflow.py
causaliq_workflow-0.1.0.dist-info/licenses/LICENSE
causaliq_workflow-0.1.0.dist-info/METADATA
causaliq_workflow-0.1.0.dist-info/WHEEL
causaliq_workflow-0.1.0.dist-info/entry_points.txt
causaliq_workflow-0.1.0.dist-info/top_level.txt
causaliq_workflow-0.1.0.dist-info/RECORD
